pinecone_hybrid_preview/__init__.py
pinecone_hybrid_preview/index.py
pinecone_hybrid_preview-0.0.2.dist-info/LICENSE
pinecone_hybrid_preview-0.0.2.dist-info/METADATA
pinecone_hybrid_preview-0.0.2.dist-info/WHEEL
pinecone_hybrid_preview-0.0.2.dist-info/top_level.txt
pinecone_hybrid_preview-0.0.2.dist-info/RECORD
