Metadata-Version: 2.1
Name: pinecone-hybrid-preview
Version: 0.0.2
Summary: Unofficial Python client for Pinecone hybrid index
Home-page: https://github.com/jamescalam/pinecone-hybrid-preview
Author: James Briggs
Author-email: jamescalam94@gmail.com
Classifier: Programming Language :: Python :: 3
Classifier: License :: OSI Approved :: MIT License
Classifier: Operating System :: OS Independent
Requires-Python: >=3.6
License-File: LICENSE
